[
  {
    "line": 1,
    "elements": [
      {
        "start_timestamp": "2021-07-12T03:33:49.601Z",
        "before": [
          {
            "result": {
              "duration": 3702000000,
              "status": "passed"
            },
            "match": {
              "location": "com.example.stepDefinitions.ProjectHooks.setUp()"
            }
          }
        ],
        "line": 4,
        "name": "Open google page:",
        "description": "",
        "id": "demo-test;open-google-page:",
        "after": [
          {
            "result": {
              "duration": 4767000000,
              "status": "passed"
            },
            "match": {
              "location": "com.example.stepDefinitions.ProjectHooks.tearDown()"
            }
          }
        ],
        "type": "scenario",
        "keyword": "Scenario",
        "steps": [
          {
            "result": {
              "duration": 2446000000,
              "status": "passed"
            },
            "line": 5,
            "name": "User launch google page",
            "match": {
              "location": "com.example.stepDefinitions.GoogleStepDefs.user_launch_google_page()"
            },
            "keyword": "Given "
          }
        ],
        "tags": [
          {
            "name": "@regression"
          }
        ]
      },
      {
        "start_timestamp": "2021-07-12T03:34:00.595Z",
        "before": [
          {
            "result": {
              "duration": 1987000000,
              "status": "passed"
            },
            "match": {
              "location": "com.example.stepDefinitions.ProjectHooks.setUp()"
            }
          }
        ],
        "line": 8,
        "name": "Open facebook page",
        "description": "",
        "id": "demo-test;open-facebook-page",
        "after": [
          {
            "result": {
              "duration": 1083000000,
              "status": "passed"
            },
            "match": {
              "location": "com.example.stepDefinitions.ProjectHooks.tearDown()"
            }
          }
        ],
        "type": "scenario",
        "keyword": "Scenario",
        "steps": [
          {
            "result": {
              "duration": 3232000000,
              "status": "passed"
            },
            "line": 9,
            "name": "User launch facebook page",
            "match": {
              "location": "com.example.stepDefinitions.GoogleStepDefs.userLaunchFacebookPage()"
            },
            "keyword": "Given "
          }
        ],
        "tags": [
          {
            "name": "@regression"
          }
        ]
      }
    ],
    "name": "Demo test",
    "description": "",
    "id": "demo-test",
    "keyword": "Feature",
    "uri": "file:src/test/resources/features/GoogleTest.feature",
    "tags": []
  }
]